<annotation>
	<folder>JPEGImages</folder>
	<filename>1247.jpg</filename>
	<path>C:\Users\86137\Desktop\VOCdevkit\VOC2007\JPEGImages\1247.jpg</path>
	<source>
		<database>Unknown</database>
	</source>
	<size>
		<width>504</width>
		<height>300</height>
		<depth>3</depth>
	</size>
	<segmented>0</segmented>
	<object>
		<name>normal</name>
		<pose>Unspecified</pose>
		<truncated>0</truncated>
		<difficult>0</difficult>
		<bndbox>
			<xmin>67</xmin>
			<ymin>12</ymin>
			<xmax>121</xmax>
			<ymax>80</ymax>
		</bndbox>
	</object>
	<object>
		<name>normal</name>
		<pose>Unspecified</pose>
		<truncated>0</truncated>
		<difficult>0</difficult>
		<bndbox>
			<xmin>70</xmin>
			<ymin>112</ymin>
			<xmax>115</xmax>
			<ymax>172</ymax>
		</bndbox>
	</object>
	<object>
		<name>normal</name>
		<pose>Unspecified</pose>
		<truncated>0</truncated>
		<difficult>0</difficult>
		<bndbox>
			<xmin>66</xmin>
			<ymin>211</ymin>
			<xmax>118</xmax>
			<ymax>273</ymax>
		</bndbox>
	</object>
</annotation>
