<annotation>
	<folder>JPEGImages</folder>
	<filename>1323.jpg</filename>
	<path>C:\Users\86137\Desktop\VOCdevkit\VOC2007\JPEGImages\1323.jpg</path>
	<source>
		<database>Unknown</database>
	</source>
	<size>
		<width>550</width>
		<height>268</height>
		<depth>3</depth>
	</size>
	<segmented>0</segmented>
	<object>
		<name>normal</name>
		<pose>Unspecified</pose>
		<truncated>0</truncated>
		<difficult>0</difficult>
		<bndbox>
			<xmin>28</xmin>
			<ymin>15</ymin>
			<xmax>84</xmax>
			<ymax>102</ymax>
		</bndbox>
	</object>
	<object>
		<name>normal</name>
		<pose>Unspecified</pose>
		<truncated>0</truncated>
		<difficult>0</difficult>
		<bndbox>
			<xmin>211</xmin>
			<ymin>6</ymin>
			<xmax>278</xmax>
			<ymax>99</ymax>
		</bndbox>
	</object>
	<object>
		<name>normal</name>
		<pose>Unspecified</pose>
		<truncated>0</truncated>
		<difficult>0</difficult>
		<bndbox>
			<xmin>394</xmin>
			<ymin>4</ymin>
			<xmax>468</xmax>
			<ymax>110</ymax>
		</bndbox>
	</object>
</annotation>
