<annotation>
	<folder>JPEGImages</folder>
	<filename>38-MaleNoGlasses-Yawning.avi_20220107_185728.144.jpg</filename>
	<path>C:\Users\86137\Desktop\VOCdevkit\VOC2007\JPEGImages\38-MaleNoGlasses-Yawning.avi_20220107_185728.144.jpg</path>
	<source>
		<database>Unknown</database>
	</source>
	<size>
		<width>640</width>
		<height>480</height>
		<depth>3</depth>
	</size>
	<segmented>0</segmented>
	<object>
		<name>normal</name>
		<pose>Unspecified</pose>
		<truncated>0</truncated>
		<difficult>0</difficult>
		<bndbox>
			<xmin>306</xmin>
			<ymin>19</ymin>
			<xmax>518</xmax>
			<ymax>320</ymax>
		</bndbox>
	</object>
</annotation>
