<annotation>
	<folder>JPEGImages</folder>
	<filename>638.jpg</filename>
	<path>C:\Users\86137\Desktop\VOCdevkit\VOC2007\JPEGImages\638.jpg</path>
	<source>
		<database>Unknown</database>
	</source>
	<size>
		<width>240</width>
		<height>179</height>
		<depth>3</depth>
	</size>
	<segmented>0</segmented>
	<object>
		<name>normal</name>
		<pose>Unspecified</pose>
		<truncated>1</truncated>
		<difficult>0</difficult>
		<bndbox>
			<xmin>4</xmin>
			<ymin>1</ymin>
			<xmax>240</xmax>
			<ymax>179</ymax>
		</bndbox>
	</object>
</annotation>
